odh_jupyter_trash_cleanup/__init__.py
odh_jupyter_trash_cleanup/_version.py
odh_jupyter_trash_cleanup/handlers.py
odh_jupyter_trash_cleanup/log.py
odh_jupyter_trash_cleanup/test_empty_trash.py
odh_jupyter_trash_cleanup/trash.py
odh_jupyter_trash_cleanup/tests/__init__.py
odh_jupyter_trash_cleanup/tests/test_handlers.py
odh_jupyter_trash_cleanup-0.1.1.data/data/etc/jupyter/jupyter_server_config.d/odh_jupyter_trash_cleanup.json
odh_jupyter_trash_cleanup-0.1.1.data/data/share/jupyter/labextensions/odh-jupyter-trash-cleanup/package.json
odh_jupyter_trash_cleanup-0.1.1.data/data/share/jupyter/labextensions/odh-jupyter-trash-cleanup/schemas/odh-jupyter-trash-cleanup/package.json.orig
odh_jupyter_trash_cleanup-0.1.1.data/data/share/jupyter/labextensions/odh-jupyter-trash-cleanup/schemas/odh-jupyter-trash-cleanup/plugin.json
odh_jupyter_trash_cleanup-0.1.1.data/data/share/jupyter/labextensions/odh-jupyter-trash-cleanup/static/262.474f0a7bec606501744c.js
odh_jupyter_trash_cleanup-0.1.1.data/data/share/jupyter/labextensions/odh-jupyter-trash-cleanup/static/878.4c267f2e592bd949b1d3.js
odh_jupyter_trash_cleanup-0.1.1.data/data/share/jupyter/labextensions/odh-jupyter-trash-cleanup/static/remoteEntry.f79ff22a3245b361fb97.js
odh_jupyter_trash_cleanup-0.1.1.data/data/share/jupyter/labextensions/odh-jupyter-trash-cleanup/static/style.js
odh_jupyter_trash_cleanup-0.1.1.data/data/share/jupyter/labextensions/odh-jupyter-trash-cleanup/static/third-party-licenses.json
odh_jupyter_trash_cleanup-0.1.1.data/data/share/jupyter/labextensions/odh-jupyter-trash-cleanup/install.json
odh_jupyter_trash_cleanup-0.1.1.dist-info/METADATA
odh_jupyter_trash_cleanup-0.1.1.dist-info/WHEEL
odh_jupyter_trash_cleanup-0.1.1.dist-info/licenses/LICENSE
odh_jupyter_trash_cleanup-0.1.1.dist-info/RECORD
